odoo9_addon_sale_fixed_discount-9.0.1.0.0.99.dev5-py3.6-nspkg.pth
odoo_addons/sale_fixed_discount/README.rst
odoo_addons/sale_fixed_discount/__init__.py
odoo_addons/sale_fixed_discount/__openerp__.py
odoo_addons/sale_fixed_discount/i18n/ca.po
odoo_addons/sale_fixed_discount/i18n/es.po
odoo_addons/sale_fixed_discount/i18n/sale_fixed_discount.pot
odoo_addons/sale_fixed_discount/models/__init__.py
odoo_addons/sale_fixed_discount/models/sale_order.py
odoo_addons/sale_fixed_discount/reports/report_sale_order.xml
odoo_addons/sale_fixed_discount/static/description/icon.png
odoo_addons/sale_fixed_discount/tests/__init__.py
odoo_addons/sale_fixed_discount/tests/test_sale_fixed_discount.py
odoo_addons/sale_fixed_discount/views/sale_order_view.xml
odoo9_addon_sale_fixed_discount-9.0.1.0.0.99.dev5.dist-info/METADATA
odoo9_addon_sale_fixed_discount-9.0.1.0.0.99.dev5.dist-info/WHEEL
odoo9_addon_sale_fixed_discount-9.0.1.0.0.99.dev5.dist-info/namespace_packages.txt
odoo9_addon_sale_fixed_discount-9.0.1.0.0.99.dev5.dist-info/top_level.txt
odoo9_addon_sale_fixed_discount-9.0.1.0.0.99.dev5.dist-info/RECORD
